hocoto/__init__.py
hocoto/deprecated_profilenames.py
hocoto/fake_paramset.py
hocoto/homematic_day_profile.py
hocoto/homematic_event_handler.py
hocoto/homematic_profile.py
hocoto/modesetter.py
hocoto/parse_options_manager.py
hocoto/profile_manager.py
hocoto/tools.py
hocoto/weekdays.py
hocoto-0.6.0.dist-info/LICENSE
hocoto-0.6.0.dist-info/METADATA
hocoto-0.6.0.dist-info/WHEEL
hocoto-0.6.0.dist-info/entry_points.txt
hocoto-0.6.0.dist-info/pbr.json
hocoto-0.6.0.dist-info/top_level.txt
hocoto-0.6.0.dist-info/RECORD
