Metadata-Version: 2.1
Name: hocoto
Version: 0.6.0
Summary: Homematic Commanline Tools (HoCoTo)
Home-page: https://none
Author: Marcus Hardt
Author-email: marcus@hardt-it.de
License: MIT
Project-URL: Bug Tracker, https://none
Project-URL: Documentation, https://none
Platform: UNKNOWN
Classifier: Development Status :: 3 - Alpha
Classifier: Environment :: Console
Classifier: Intended Audience :: Developers
Classifier: Intended Audience :: Information Technology
Classifier: Intended Audience :: Science/Research
Classifier: License :: OSI Approved :: MIT License
Classifier: Operating System :: OS Independent
Classifier: Natural Language :: English
Classifier: Programming Language :: Python
Classifier: Programming Language :: Python :: 3
Classifier: Topic :: Utilities
Requires-Dist: configargparse
Requires-Dist: homegear
